quiver_pdb-0.7.0.dist-info/METADATA
quiver_pdb-0.7.0.dist-info/WHEEL
quiver_pdb-0.7.0.dist-info/entry_points.txt
quiver_pdb-0.7.0.dist-info/licenses/LICENSE
quiver_pdb/qvrename.py
quiver_pdb/qvscorefile.py
quiver_pdb/qvextract.py
quiver_pdb/qvslice.py
quiver_pdb/qvextractspecific.py
quiver_pdb/qvsplit.py
quiver_pdb/qvls.py
quiver_pdb/qvfrompdbs.py
quiver_pdb/__init__.py
quiver_pdb/quiver_pdb.cpython-311-x86_64-linux-gnu.so
quiver_pdb-0.7.0.dist-info/RECORD
