Metadata-Version: 2.4
Name: quiver-pdb
Version: 0.7.0
Classifier: Programming Language :: Rust
Classifier: Programming Language :: Python :: Implementation :: CPython
Classifier: Programming Language :: Python :: Implementation :: PyPy
Requires-Dist: click>=8.1.8
License-File: LICENSE
Summary: Quiver files are simply one large file with the contents of many smaller files inside of them.
Author-email: rabbitQ <deepthough@postech.ac.kr>
License: MIT
Requires-Python: >=3.11
